giga/__init__.py
giga/cli.py
giga/config.py
giga/ensure.py
giga/ensurer.py
giga/error.py
giga/exec.py
giga/group.py
giga/method.py
giga/sync.py
giga/system.py
giga/task.py
giga/unix.py
giga/utils.py
giga/configs/__init__.py
giga/configs/asset.py
giga/configs/docker.py
giga/configs/fs.py
giga/configs/git.py
giga/configs/helm.py
giga/configs/kube.py
giga/configs/kubespray.py
giga/configs/minikube.py
giga/configs/netdata.py
giga/configs/python.py
giga/configs/systemd.py
giga/configs/updatedb.py
giga/configs/wget.py
giga/configs/os/__init__.py
giga/configs/os/debian.py
giga/configs/os/redhat.py
giga-0.0.7.dist-info/LICENSE
giga-0.0.7.dist-info/METADATA
giga-0.0.7.dist-info/WHEEL
giga-0.0.7.dist-info/entry_points.txt
giga-0.0.7.dist-info/top_level.txt
giga-0.0.7.dist-info/zip-safe
giga-0.0.7.dist-info/RECORD
